README.md
setup.py
my_youtube_package/__init__.py
my_youtube_package/combined_api.py
my_youtube_package/data_api.py
my_youtube_package/transcript_api.py
my_youtube_package.egg-info/PKG-INFO
my_youtube_package.egg-info/SOURCES.txt
my_youtube_package.egg-info/dependency_links.txt
my_youtube_package.egg-info/requires.txt
my_youtube_package.egg-info/top_level.txt
tests/__init__.py
tests/test_combined_api.py
tests/test_data_api.py
tests/test_transcript_api.py