Metadata-Version: 2.1
Name: my-youtube-package
Version: 0.1.0
Summary: A package to interact with YouTube Data API and YouTube Transcript API
Home-page: 
Author: Souvik Sen
Author-email: souviks1008@gmail.com
Classifier: Programming Language :: Python :: 3
Classifier: License :: OSI Approved :: MIT License
Classifier: Operating System :: OS Independent
Requires-Python: >=3.6
